mdscope/__init__.py
mdscope/compute.py
mdscope/graph.py
mdscope/io.py
mdscope/mdscope.py
mdscope/x_ray_scattering_cpu.py
mdscope/x_ray_scattering_gpu.py
mdscope/x_ray/AtomFormFactor.py
mdscope/x_ray/IUCrAtomDataBase.py
mdscope-0.2.0.dist-info/AUTHORS.rst
mdscope-0.2.0.dist-info/LICENSE
mdscope-0.2.0.dist-info/METADATA
mdscope-0.2.0.dist-info/WHEEL
mdscope-0.2.0.dist-info/top_level.txt
mdscope-0.2.0.dist-info/RECORD
