Metadata-Version: 2.2
Name: mdscope
Version: 0.2.0
Summary: A python package to post-process molecular dynamics simulations.
Author-email: Jingcun Fan <jcfan@stanford.edu>
Maintainer-email: Jingcun Fan <jcfan@stanford.edu>
License: MIT license
Project-URL: bugs, https://github.com/funwithfan/mdscope/issues
Project-URL: changelog, https://github.com/funwithfan/mdscope/blob/master/changelog.md
Project-URL: homepage, https://github.com/funwithfan/mdscope
License-File: LICENSE
License-File: AUTHORS.rst
Provides-Extra: dev
Requires-Dist: coverage; extra == "dev"
Requires-Dist: mypy; extra == "dev"
Requires-Dist: pytest; extra == "dev"
Requires-Dist: ruff; extra == "dev"
